hawcsimulator/__init__.py
hawcsimulator/_version.py
hawcsimulator/appconfig.py
hawcsimulator/simulator.py
hawcsimulator/ali/__init__.py
hawcsimulator/ali/calibration.py
hawcsimulator/ali/inst_model.py
hawcsimulator/ali/por.py
hawcsimulator/ali/configurations/__init__.py
hawcsimulator/ali/configurations/base.py
hawcsimulator/ali/configurations/ideal_spectrograph.py
hawcsimulator/ali/steps/__init__.py
hawcsimulator/ali/steps/fer.py
hawcsimulator/ali/steps/ideal_inst.py
hawcsimulator/ali/steps/l2.py
hawcsimulator/ali/steps/por.py
hawcsimulator/atmosphere/__init__.py
hawcsimulator/atmosphere/aerosol.py
hawcsimulator/atmosphere/earthcare/__init__.py
hawcsimulator/atmosphere/ompscalera/__init__.py
hawcsimulator/datastructures/__init__.py
hawcsimulator/datastructures/atmosphere.py
hawcsimulator/datastructures/base.py
hawcsimulator/datastructures/viewinggeo.py
hawcsimulator/fer/__init__.py
hawcsimulator/geometry/__init__.py
hawcsimulator/geometry/observation.py
hawcsimulator/show/__init__.py
hawcsimulator/show/calibration.py
hawcsimulator/show/inst_model.py
hawcsimulator/show/por.py
hawcsimulator/show/configurations/__init__.py
hawcsimulator/show/configurations/base.py
hawcsimulator/show/configurations/ideal.py
hawcsimulator/show/steps/__init__.py
hawcsimulator/show/steps/fer.py
hawcsimulator/show/steps/ideal_inst.py
hawcsimulator/show/steps/l2.py
hawcsimulator/show/steps/por.py
hawcsimulator/steps/__init__.py
hawcsimulator/steps/atmosphere.py
hawcsimulator/steps/limb_observation.py
hawcsimulator-2025.3.0.dist-info/LICENSE
hawcsimulator-2025.3.0.dist-info/METADATA
hawcsimulator-2025.3.0.dist-info/WHEEL
hawcsimulator-2025.3.0.dist-info/top_level.txt
hawcsimulator-2025.3.0.dist-info/RECORD
