Metadata-Version: 2.2
Name: hawcsimulator
Version: 2025.3.0
Summary: HAWCsat simulator package
Author-email: Daniel Zawada <daniel.zawada@usask.ca>
Classifier: Development Status :: 4 - Beta
Classifier: Programming Language :: Python :: 3 :: Only
Classifier: Programming Language :: Python :: 3.11
Classifier: Programming Language :: Python :: 3.12
Classifier: Programming Language :: Python :: 3.13
Requires-Python: >=3.11
License-File: LICENSE
Requires-Dist: numpy
Requires-Dist: sasktran2
Requires-Dist: netcdf4
Requires-Dist: appdirs
Requires-Dist: numba>0.55
Requires-Dist: aliprocessing
Requires-Dist: skretrieval
Requires-Dist: showlib
Requires-Dist: sf-hamilton
Requires-Dist: hitran-api
Provides-Extra: test
Requires-Dist: pytest; extra == "test"
